LICENSE
README.md
setup.cfg
setup.py
doc_transformers/__init__.py
doc_transformers/parser.py
doc_transformers.egg-info/PKG-INFO
doc_transformers.egg-info/SOURCES.txt
doc_transformers.egg-info/dependency_links.txt
doc_transformers.egg-info/not-zip-safe
doc_transformers.egg-info/requires.txt
doc_transformers.egg-info/top_level.txt